firebatch/__init__.py
firebatch/__main__.py
firebatch/cli.py
firebatch/endcoding.py
firebatch/firestore_client.py
firebatch/operations.py
firebatch/utils.py
firebatch-1.1.1.dist-info/LICENSE
firebatch-1.1.1.dist-info/METADATA
firebatch-1.1.1.dist-info/WHEEL
firebatch-1.1.1.dist-info/entry_points.txt
firebatch-1.1.1.dist-info/RECORD
