Metadata-Version: 2.1
Name: firebatch
Version: 1.1.1
Summary: A CLI and library for Firestore batch operations
License: MIT
Author: Alexander Balasch
Requires-Python: >=3.12,<4.0
Classifier: License :: OSI Approved :: MIT License
Classifier: Programming Language :: Python :: 3
Classifier: Programming Language :: Python :: 3.12
Requires-Dist: click (>=8.1.7,<9.0.0)
Requires-Dist: google-cloud-firestore (>=2.15.0,<3.0.0)
Requires-Dist: tqdm (>=4.66.2,<5.0.0)
Project-URL: Bug Tracker, https://github.com/thunderbug1/firebatch/issues
Project-URL: GitHub Repository, https://github.com/thunderbug1/firebatch
